queue_utilities/__init__.py
queue_utilities/as_thread.py
queue_utilities/attach_queue.py
queue_utilities/multicast.py
queue_utilities/multiplex.py
queue_utilities/pipe.py
queue_utilities/py.typed
queue_utilities/select.py
queue_utilities/ticker.py
queue_utilities/timer.py
queue_utilities-0.0.12.dist-info/LICENSE
queue_utilities-0.0.12.dist-info/METADATA
queue_utilities-0.0.12.dist-info/WHEEL
queue_utilities-0.0.12.dist-info/top_level.txt
queue_utilities-0.0.12.dist-info/RECORD
