Metadata-Version: 2.1
Name: queue-utilities
Version: 0.0.12
Summary: A collection of helpful queue utilities. Pipes, timers, tickers, multiplexors, multicasters and queue select.
Home-page: https://github.com/jaycosaur/queue-utilities
Author: Jacob Richter
Author-email: jaycorichter@gmail.com
License: UNKNOWN
Platform: UNKNOWN
Classifier: Programming Language :: Python :: 3
Classifier: License :: OSI Approved :: MIT License
Classifier: Operating System :: OS Independent
